leanprompt/__init__.py
leanprompt/core.py
leanprompt/guard.py
leanprompt-0.1.3.dist-info/licenses/LICENSE
leanprompt-0.1.3.dist-info/METADATA
leanprompt-0.1.3.dist-info/WHEEL
leanprompt-0.1.3.dist-info/top_level.txt
leanprompt-0.1.3.dist-info/RECORD
